Workbook

Sheet Assumptions
A1: Maison Lumière · P2P — ROI Assumptions
A3: Assumption | B3: Value | C3: Unit | D3: Source / justification (labelled)
A4: Loaded finance rate | B4: 45 | C4: €/h | D4: Mid-range EU finance-clerk loaded cost — VALIDATE with client
A5: Invoice volume (monthly) | B5: 420 | C5: inv/mo | D5: Assumed full-property SME 5★ — LOW confidence, pilot validates
A6: Invoice volume (annual) | B6: =B5*12 -> 5040 | C6: inv/yr | D6: Computed
A7: Manual cost / invoice | B7: 12 | C7: € | D7: HighRadius/Quadient/Nanonets 2025 (vendor → directional)
A8: Automated cost / invoice | B8: 3.9 | C8: € | D8: ~70% reduction (directional)
A9: Touchless rate at maturity | B9: 0.78 | C9: % | D9: Modelled pilot learning curve
A10: Productive hours / FTE / yr | B10: 1600 | C10: h | D10: Standard net-of-leave assumption
A11: Pilot cost (one-off) | B11: 20000 | C11: € | D11: Project 5 cost model (10-week pilot)
A12: Rollout cost (Year 1) | B12: 8000 | C12: € | D12: Project 5 cost model
A13: Ongoing run cost / yr | B13: 13000 | C13: € | D13: LLM €2k + hosting €2k + support €5k + tuning €4k
A14: 3-way match — labour saved | B14: 26000 | C14: €/yr | D14: Modelled (matching time eliminated)
A15: 3-way match — cash recovered | B15: 10000 | C15: €/yr | D15: ~0.6% of ~€1.8M spend (overbilling/variance)
A16: Inventory — waste/shrinkage cut | B16: 9000 | C16: €/yr | D16: Modelled
A17: Inventory — stock-entry labour | B17: 19500 | C17: €/yr | D17: Modelled (manual stock entry eliminated)
A18: Working-capital release (one-off) | B18: 15000 | C18: € | D18: ~10% of tied-up F&B stock (cash, not P&L)

Sheet ROI Model
A1: ROI Model — formula: ROI = Net Benefit ÷ Total Cost
A3: A · Annual benefit build-up (full tool)
A4: AP automation — processing time saved | B4: 42000 | C4: modelled ≈ annual volume × per-invoice saving (€12→€3.9); Project 5 model
A5: 3-way match — labour saved | B5: =Assumptions!B14 -> 26000
A6: 3-way match — cash recovered | B6: =Assumptions!B15 -> 10000
A7: Inventory — waste/shrinkage cut | B7: =Assumptions!B16 -> 9000
A8: Inventory — stock-entry labour | B8: =Assumptions!B17 -> 19500
A9: Gross recurring benefit | B9: =SUM(B4:B8) -> 106500
A10: Less: ongoing run cost | B10: =-Assumptions!B13 -> -13000
A11: Net recurring benefit | B11: =B9+B10 -> 93500
A12: One-off working-capital release | B12: =Assumptions!B18 -> 15000
A14: B · Conservative case — AP automation ONLY (headline)
A15: AP gross saving / yr | B15: =B4 -> 42000
A16: Year-1 cost (pilot + rollout + run) | B16: =Assumptions!B11+Assumptions!B12+Assumptions!B13 -> 41000
A17: Year-1 net benefit | B17: =B15-B16 -> 1000
A18: Year-1 ROI | B18: =B17/B16 -> 0.024390244
A19: 3-year total cost | B19: =Assumptions!B11+Assumptions!B12+3*Assumptions!B13 -> 67000
A20: 3-year gross saving | B20: =3*B15 -> 126000
A21: 3-year net benefit | B21: =B20-B19 -> 59000
A22: 3-year ROI | B22: =B21/B19 -> 0.88059701
A23: Payback incl. pilot (months) | B23: =B16/(B15/12) -> 11.714286
A24: Payback ongoing (months) | B24: =Assumptions!B13/(B15/12) -> 3.7142857
A26: C · Full-tool case (illustrative)
A27: 36-month total cost | B27: =B19 -> 67000
A28: 36-month net benefit | B28: =3*B11-(Assumptions!B11+Assumptions!B12) -> 252500
A29: 36-month ROI | B29: =B28/B27 -> 3.7686567
A30: FTE freed (labour pools only) | B30: =(B4+Assumptions!B14+Assumptions!B17)/Assumptions!B4/Assumptions!B10 -> 1.2152778
A32: Volume-driven: below ~250 invoices/mo the Year-1 return turns negative — the pilot gate confirms real volume first.

Sheet Risk Matrix
A1: Risk Matrix — Risk level = Likelihood × Impact
A3: # | B3: Category | C3: Risk | D3: Likelihood (1-5) | E3: Impact (1-5) | F3: Score | G3: Level | H3: Mitigation
A4: R1 | B4: Technical | C4: Auto-coding accuracy below target on the real invoice mix (scans, new vendors, hallucinated values) | D4: 3 | E4: 4 | F4: =D4*E4 -> 12 | G4: =IF(F4>=12,"High",IF(F4>=6,"Medium","Low")) -> High | H4: Human reviews every entry; confidence-threshold routing; pilot backtest before scaling
A5: R2 | B5: Regulatory | C5: Data security — invoices carry vendor PII processed by third-party LLM / US services | D5: 3 | E5: 4 | F5: =D5*E5 -> 12 | G5: =IF(F5>=12,"High",IF(F5>=6,"Medium","Low")) -> High | H5: DPA per vendor; EU-region processing; data minimisation; no full ledger ingested
A6: R3 | B6: Operational | C6: Invoice volume too low for the ROI to clear | D6: 2 | E6: 4 | F6: =D6*E6 -> 8 | G6: =IF(F6>=12,"High",IF(F6>=6,"Medium","Low")) -> Medium | H6: Confirm real volume up front; pilot gate holds/kills if thin
A7: R4 | B7: Operational | C7: Change resistance / finance-team distrust of 'AI doing the books' | D7: 3 | E7: 3 | F7: =D7*E7 -> 9 | G7: =IF(F7>=12,"High",IF(F7>=6,"Medium","Low")) -> Medium | H7: 'Second set of eyes' framing; no headcount cuts; training; team keeps final say
A8: R5 | B8: Ethical | C8: Automation bias / over-reliance — staff rubber-stamp AI without genuine review | D8: 3 | E8: 4 | F8: =D8*E8 -> 12 | G8: =IF(F8>=12,"High",IF(F8>=6,"Medium","Low")) -> High | H8: Source shown beside proposal; non-skippable review; spot-audits; staff stay accountable
A9: R6 | B9: Ethical | C9: Misrepresentation in AI-drafted dispute e-mails (tone, wrong figures) | D9: 2 | E9: 3 | F9: =D9*E9 -> 6 | G9: =IF(F9>=12,"High",IF(F9>=6,"Medium","Low")) -> Medium | H9: Human reviews & sends every e-mail; AI-assistance disclosure; figures from validated match
A10: R7 | B10: Technical | C10: Invoice quality / format drift degrading extraction | D10: 3 | E10: 2 | F10: =D10*E10 -> 6 | G10: =IF(F10>=12,"High",IF(F10>=6,"Medium","Low")) -> Medium | H10: Exception routing + manual fallback; rising e-invoice share reduces this over time
A11: R8 | B11: Regulatory | C11: EU AI Act / GDPR misstep (wrong classification, missing DPIA, undocumented transfer) | D11: 2 | E11: 4 | F11: =D11*E11 -> 8 | G11: =IF(F11>=12,"High",IF(F11>=6,"Medium","Low")) -> Medium | H11: Limited-risk classification + DPIA + technical file; EU-region processing; retention policy
A12: R9 | B12: Operational | C12: Tooling cost overrun / vendor pricing change / lock-in | D12: 2 | E12: 3 | F12: =D12*E12 -> 6 | G12: =IF(F12>=12,"High",IF(F12>=6,"Medium","Low")) -> Medium | H12: Usage caps; standard formats (EN 16931/Peppol); portable architecture
